lol/__init__.py
lol/api.py
lol/data/bash_huge.classifier2
lol/data/bash_huge.known
lol/data/bash_huge.vectorizer
lol/data/cmd_huge.classifier2
lol/data/cmd_huge.known
lol/data/cmd_huge.vectorizer
lol/model/__init__.py
lol/model/constants.py
lol/model/utils.py
lolc-0.1.0.6.data/data/lol/bash_huge.classifier2
lolc-0.1.0.6.data/data/lol/bash_huge.known
lolc-0.1.0.6.data/data/lol/bash_huge.vectorizer
lolc-0.1.0.6.data/data/lol/cmd_huge.classifier2
lolc-0.1.0.6.data/data/lol/cmd_huge.known
lolc-0.1.0.6.data/data/lol/cmd_huge.vectorizer
lolc-0.1.0.6.dist-info/LICENSE
lolc-0.1.0.6.dist-info/METADATA
lolc-0.1.0.6.dist-info/WHEEL
lolc-0.1.0.6.dist-info/top_level.txt
lolc-0.1.0.6.dist-info/RECORD
