Metadata-Version: 2.1
Name: lolc
Version: 0.1.0.6
Summary: Python module for detecting password, api keys hashes and any other string that resembles a randomly generated character sequence.
Home-page: https://github.com/adobe/libLOL
Author: Multiple authors
Author-email: tiberiu44@gmail.com
License: UNKNOWN
Platform: UNKNOWN
Classifier: Programming Language :: Python :: 3.0
Classifier: License :: OSI Approved :: Apache Software License
Classifier: Operating System :: OS Independent
License-File: LICENSE
Requires-Dist: pyre2 (>=0.3.6)
Requires-Dist: ipdb (>=0.13.7)
Requires-Dist: nltk (>=3.6.2)
Requires-Dist: numpy (>=1.20.3)
Requires-Dist: pandas (>=1.2.4)
Requires-Dist: tqdm (>=4.60.0)
Requires-Dist: joblib (>=1.0.1)
Requires-Dist: scikit-learn (>=0.24.2)
